Metadata-Version: 2.1
Name: samesite-compat-check
Version: 0.1.3
Summary: A port of Chrome's browser compatibility check for SameSite=None cookies
Home-page: https://github.com/peergradeio/samesite-compat-check
Author: Malthe Jørgensen
Author-email: malthe.jorgensen@gmail.com
License: Apache License 2.0
Platform: UNKNOWN
Classifier: Development Status :: 4 - Beta
Classifier: License :: OSI Approved :: Apache Software License
Classifier: Programming Language :: Python
Classifier: Programming Language :: Python :: 2
Classifier: Programming Language :: Python :: 2.7
Classifier: Programming Language :: Python :: 3
Classifier: Programming Language :: Python :: 3.4
Classifier: Programming Language :: Python :: 3.5
Classifier: Programming Language :: Python :: 3.6
Classifier: Programming Language :: Python :: 3.7
